{
    "officers": [
        {
            "name": "Mr. Ryan  Cohen",
            "title": "President, CEO & Executive Chairman",
            "yearBorn": 1986,
            "age": 38,
            "totalPay": 268553,
            "source": "yfinance"
        },
        {
            "name": "Mr. Daniel William Moore",
            "title": "Principal Accounting Officer & Principal Financial Officer",
            "yearBorn": 1984,
            "age": 40,
            "totalPay": 221492,
            "source": "yfinance"
        },
        {
            "name": "Mr. Mark Haymond Robinson",
            "title": "General Counsel & Secretary",
            "yearBorn": 1979,
            "age": 45,
            "totalPay": 200000,
            "source": "yfinance"
        }
    ]
}