{
  "address1": "Praia de Botafogo 186",
  "address2": "offices 1101, 1701 and 1801 Botafogo",
  "city": "Rio De Janeiro",
  "state": "RJ",
  "zip": "22250-145",
  "country": "Brazil",
  "phone": "55 21 3485 5000",
  "website": "https://www.vale.com",
  "industry": "Other Industrial Metals & Mining",
  "industryKey": "other-industrial-metals-mining",
  "industryDisp": "Other Industrial Metals & Mining",
  "sector": "Basic Materials",
  "sectorKey": "basic-materials",
  "sectorDisp": "Basic Materials",
  "longBusinessSummary": "Vale S.A., together with its subsidiaries, produces and sells iron ore, iron ore pellets, nickel, and copper in Brazil and internationally. The company operates through Iron Solutions and Energy Transition Materials segments. The Iron Solutions segment produces and extracts iron ore and pellets, and other ferrous products; and provides related logistic services. The Energy Transition Materials segment produces and extracts nickel; and its by-products, such as gold, silver, cobalt, precious metals, and others, as well as copper used in the construction sector to produce pipes and electrical wires. The company was formerly known as Companhia Vale do Rio Doce and changed its name to Vale S.A. in May 2009. Vale S.A. was founded in 1942 and is headquartered in Rio De Janeiro, Brazil.",
  "fullTimeEmployees": 64616,
  "companyOfficers": [
    {
      "maxAge": 1,
      "name": "Mr. Gustavo Duarte Pimenta",
      "age": 46,
      "title": "President & CEO",
      "yearBorn": 1978,
      "exercisedValue": 0,
      "unexercisedValue": 0
    },
    {
      "maxAge": 1,
      "name": "Mr. Marcelo Feriozzi Bacci",
      "age": 54,
      "title": "Executive VP of Finance & Investor Relations",
      "yearBorn": 1970,
      "exercisedValue": 0,
      "unexercisedValue": 0
    },
    {
      "maxAge": 1,
      "name": "Mr. Carlos Henrique Senna Medeiros",
      "age": 61,
      "title": "Executive Vice President of Operations",
      "yearBorn": 1963,
      "exercisedValue": 0,
      "unexercisedValue": 0
    },
    {
      "maxAge": 1,
      "name": "Mr. Rafael Jabur Bittar",
      "age": 44,
      "title": "Executive Vice President of Technical",
      "yearBorn": 1980,
      "exercisedValue": 0,
      "unexercisedValue": 0
    },
    {
      "maxAge": 1,
      "name": "Mr. Thiago K. Lofiego C.F.A.",
      "title": "Director & Head of Investor Relations",
      "exercisedValue": 0,
      "unexercisedValue": 0
    },
    {
      "maxAge": 1,
      "name": "Mr. Denis  Cuenca",
      "title": "Chief Compliance Officer",
      "exercisedValue": 0,
      "unexercisedValue": 0
    },
    {
      "maxAge": 1,
      "name": "Ms. Catia Valeria Porto",
      "title": "Executive Vice President of people",
      "exercisedValue": 0,
      "unexercisedValue": 0
    },
    {
      "maxAge": 1,
      "name": "Mr. Eduardo  de Salles Bartolomeo",
      "age": 60,
      "title": "Advisor",
      "yearBorn": 1964,
      "exercisedValue": 0,
      "unexercisedValue": 0
    },
    {
      "maxAge": 1,
      "name": "Mr. Rog\u00e9rio Tavares Nogueira",
      "title": "Executive Vice President of Commercial & Development",
      "exercisedValue": 0,
      "unexercisedValue": 0
    },
    {
      "maxAge": 1,
      "name": "Mr. Alexandre Silva D'Ambrosio",
      "age": 62,
      "title": "Executive Vice-President of Corporate & External Affairs",
      "yearBorn": 1962,
      "exercisedValue": 0,
      "unexercisedValue": 0
    }
  ],
  "executiveTeam": [],
  "maxAge": 86400,
  "priceHint": 2,
  "previousClose": 9.37,
  "open": 9.48,
  "dayLow": 9.41,
  "dayHigh": 9.51,
  "regularMarketPreviousClose": 9.37,
  "regularMarketOpen": 9.48,
  "regularMarketDayLow": 9.41,
  "regularMarketDayHigh": 9.51,
  "dividendRate": 1.38,
  "dividendYield": 14.71,
  "exDividendDate": 1741564800,
  "payoutRatio": 0.6047,
  "fiveYearAvgDividendYield": 8.62,
  "beta": 1.061,
  "trailingPE": 6.7913666,
  "forwardPE": 4.604878,
  "volume": 25600244,
  "regularMarketVolume": 25600244,
  "averageVolume": 31778193,
  "averageVolume10days": 25572640,
  "averageDailyVolume10Day": 25572640,
  "bid": 9.41,
  "ask": 9.47,
  "bidSize": 745,
  "askSize": 208,
  "marketCap": 40421888000,
  "fiftyTwoWeekLow": 8.06,
  "fiftyTwoWeekHigh": 12.15,
  "priceToSalesTrailing12Months": 0.19109745,
  "fiftyDayAverage": 9.5396,
  "twoHundredDayAverage": 9.86875,
  "trailingAnnualDividendRate": 4.756,
  "trailingAnnualDividendYield": 0.50757736,
  "currency": "USD",
  "tradeable": false,
  "enterpriseValue": 130460270592,
  "profitMargins": 0.14875,
  "floatShares": 3982429106,
  "sharesOutstanding": 4268780032,
  "sharesShort": 83612733,
  "sharesShortPriorMonth": 93864787,
  "sharesShortPreviousMonthDate": 1744675200,
  "dateShortInterest": 1747267200,
  "sharesPercentSharesOut": 0.0196,
  "heldPercentInsiders": 0.00014,
  "heldPercentInstitutions": 0.17103,
  "shortRatio": 3.27,
  "shortPercentOfFloat": 0.0196,
  "impliedSharesOutstanding": 4281979904,
  "bookValue": 47.34,
  "priceToBook": 0.19940853,
  "lastFiscalYearEnd": 1735603200,
  "nextFiscalYearEnd": 1767139200,
  "mostRecentQuarter": 1743379200,
  "earningsQuarterlyGrowth": -0.015,
  "netIncomeToCommon": 31465000960,
  "trailingEps": 1.39,
  "forwardEps": 2.05,
  "lastSplitFactor": "2:1",
  "lastSplitDate": 1189641600,
  "enterpriseToRevenue": 0.617,
  "enterpriseToEbitda": 1.762,
  "52WeekChange": -0.2165975,
  "SandP52WeekChange": 0.1202575,
  "lastDividendValue": 0.373,
  "lastDividendDate": 1741564800,
  "quoteType": "EQUITY",
  "currentPrice": 9.44,
  "targetHighPrice": 16.1,
  "targetLowPrice": 8.0,
  "targetMeanPrice": 12.21375,
  "targetMedianPrice": 12.0,
  "recommendationMean": 2.16,
  "recommendationKey": "buy",
  "numberOfAnalystOpinions": 24,
  "totalCash": 22958999552,
  "totalCashPerShare": 5.378,
  "ebitda": 74029998080,
  "totalDebt": 106486996992,
  "quickRatio": 0.547,
  "currentRatio": 1.11,
  "totalRevenue": 211524993024,
  "debtToEquity": 51.02,
  "revenuePerShare": 49.531,
  "returnOnAssets": 0.07763,
  "returnOnEquity": 0.15003,
  "grossProfits": 74990002176,
  "freeCashflow": 20958375936,
  "operatingCashflow": 42103001088,
  "earningsGrowth": -0.01,
  "revenueGrowth": 0.132,
  "grossMargins": 0.35452,
  "ebitdaMargins": 0.34998,
  "operatingMargins": 0.273,
  "financialCurrency": "BRL",
  "symbol": "VALE",
  "language": "en-US",
  "region": "US",
  "typeDisp": "Equity",
  "quoteSourceName": "Nasdaq Real Time Price",
  "triggerable": true,
  "customPriceAlertConfidence": "HIGH",
  "postMarketChangePercent": -0.316733,
  "postMarketPrice": 9.4101,
  "postMarketChange": -0.0298996,
  "regularMarketChange": 0.0699997,
  "regularMarketDayRange": "9.41 - 9.51",
  "shortName": "VALE S.A.",
  "longName": "Vale S.A.",
  "hasPrePostMarketData": true,
  "firstTradeDateMilliseconds": 1016721000000,
  "fullExchangeName": "NYSE",
  "averageDailyVolume3Month": 31778193,
  "fiftyTwoWeekLowChange": 1.3799992,
  "fiftyTwoWeekLowChangePercent": 0.17121577,
  "fiftyTwoWeekRange": "8.06 - 12.15",
  "fiftyTwoWeekHighChange": -2.71,
  "fiftyTwoWeekHighChangePercent": -0.22304527,
  "fiftyTwoWeekChangePercent": -21.65975,
  "dividendDate": 1742515200,
  "earningsTimestamp": 1745539202,
  "earningsTimestampStart": 1753297200,
  "earningsTimestampEnd": 1753729200,
  "earningsCallTimestampStart": 1745589600,
  "earningsCallTimestampEnd": 1745589600,
  "isEarningsDateEstimate": true,
  "epsTrailingTwelveMonths": 1.39,
  "epsForward": 2.05,
  "epsCurrentYear": 1.78967,
  "corporateActions": [],
  "postMarketTime": 1748563055,
  "regularMarketTime": 1748548802,
  "exchange": "NYQ",
  "messageBoardId": "finmb_874225",
  "exchangeTimezoneName": "America/New_York",
  "exchangeTimezoneShortName": "EDT",
  "gmtOffSetMilliseconds": -14400000,
  "market": "us_market",
  "esgPopulated": false,
  "regularMarketChangePercent": 0.747062,
  "regularMarketPrice": 9.44,
  "marketState": "POSTPOST",
  "priceEpsCurrentYear": 5.2747154,
  "fiftyDayAverageChange": -0.09960079,
  "fiftyDayAverageChangePercent": -0.010440772,
  "twoHundredDayAverageChange": -0.42875004,
  "twoHundredDayAverageChangePercent": -0.043445226,
  "sourceInterval": 15,
  "exchangeDataDelayedBy": 0,
  "averageAnalystRating": "2.2 - Buy",
  "cryptoTradeable": false,
  "displayName": "Vale",
  "trailingPegRatio": null
}