[
  {
    "month": "2024-04-01",
    "avg_price": 16.6747271798,
    "min_price": 16.2600002289,
    "max_price": 17.2339992523,
    "days_with_data": 22
  },
  {
    "month": "2024-05-01",
    "avg_price": 16.2416364496,
    "min_price": 15.0740003586,
    "max_price": 16.968000412,
    "days_with_data": 22
  },
  {
    "month": "2024-06-01",
    "avg_price": 16.7081053382,
    "min_price": 15.9259996414,
    "max_price": 17.4459991455,
    "days_with_data": 19
  },
  {
    "month": "2024-07-01",
    "avg_price": 18.0913635601,
    "min_price": 17.0620002747,
    "max_price": 19.2259998322,
    "days_with_data": 22
  },
  {
    "month": "2024-08-01",
    "avg_price": 17.8685456189,
    "min_price": 16.3220005035,
    "max_price": 19.5119991302,
    "days_with_data": 22
  },
  {
    "month": "2024-09-01",
    "avg_price": 18.7683999062,
    "min_price": 18.0100002289,
    "max_price": 19.7299995422,
    "days_with_data": 20
  },
  {
    "month": "2024-10-01",
    "avg_price": 18.449565224,
    "min_price": 17.5300006866,
    "max_price": 19.3600006104,
    "days_with_data": 23
  },
  {
    "month": "2024-11-01",
    "avg_price": 18.8364998817,
    "min_price": 17.7299995422,
    "max_price": 20.0499992371,
    "days_with_data": 20
  },
  {
    "month": "2024-12-01",
    "avg_price": 21.2189998627,
    "min_price": 20.0100002289,
    "max_price": 22.3799991608,
    "days_with_data": 20
  }
]