[
  {
    "week": "2024-04-01T00:00:00.000",
    "avg_price": 0.7491999984,
    "min_price": 0.7269999981,
    "max_price": 0.7699999809,
    "days_with_data": 5
  },
  {
    "week": "2024-04-08T00:00:00.000",
    "avg_price": 0.7156000018,
    "min_price": 0.6700000167,
    "max_price": 0.7369999886,
    "days_with_data": 5
  },
  {
    "week": "2024-04-15T00:00:00.000",
    "avg_price": 0.6299999833,
    "min_price": 0.621999979,
    "max_price": 0.6359999776,
    "days_with_data": 5
  },
  {
    "week": "2024-04-22T00:00:00.000",
    "avg_price": 0.6503999949,
    "min_price": 0.621999979,
    "max_price": 0.6800000072,
    "days_with_data": 5
  },
  {
    "week": "2024-04-29T00:00:00.000",
    "avg_price": 0.6574000001,
    "min_price": 0.6299999952,
    "max_price": 0.6949999928,
    "days_with_data": 5
  },
  {
    "week": "2024-05-06T00:00:00.000",
    "avg_price": 0.8027999997,
    "min_price": 0.7200000286,
    "max_price": 0.8709999919,
    "days_with_data": 5
  },
  {
    "week": "2024-05-13T00:00:00.000",
    "avg_price": 0.9406000018,
    "min_price": 0.8899999857,
    "max_price": 1.0199999809,
    "days_with_data": 5
  },
  {
    "week": "2024-05-20T00:00:00.000",
    "avg_price": 0.9664000034,
    "min_price": 0.8960000277,
    "max_price": 1.0199999809,
    "days_with_data": 5
  },
  {
    "week": "2024-05-27T00:00:00.000",
    "avg_price": 1.0699999928,
    "min_price": 1.0099999905,
    "max_price": 1.1399999857,
    "days_with_data": 4
  },
  {
    "week": "2024-06-03T00:00:00.000",
    "avg_price": 1.1180000067,
    "min_price": 1.1000000238,
    "max_price": 1.1699999571,
    "days_with_data": 5
  },
  {
    "week": "2024-06-10T00:00:00.000",
    "avg_price": 1.037199986,
    "min_price": 0.9860000014,
    "max_price": 1.0900000334,
    "days_with_data": 5
  },
  {
    "week": "2024-06-17T00:00:00.000",
    "avg_price": 1.1324999928,
    "min_price": 1.0299999714,
    "max_price": 1.25,
    "days_with_data": 4
  },
  {
    "week": "2024-06-24T00:00:00.000",
    "avg_price": 1.2779999733,
    "min_price": 1.2300000191,
    "max_price": 1.3099999428,
    "days_with_data": 5
  },
  {
    "week": "2024-07-01T00:00:00.000",
    "avg_price": 1.2350000143,
    "min_price": 1.2000000477,
    "max_price": 1.2699999809,
    "days_with_data": 4
  },
  {
    "week": "2024-07-08T00:00:00.000",
    "avg_price": 1.3960000277,
    "min_price": 1.3300000429,
    "max_price": 1.5099999905,
    "days_with_data": 5
  },
  {
    "week": "2024-07-15T00:00:00.000",
    "avg_price": 1.6700000286,
    "min_price": 1.5800000429,
    "max_price": 1.7300000191,
    "days_with_data": 5
  },
  {
    "week": "2024-07-22T00:00:00.000",
    "avg_price": 1.6619999886,
    "min_price": 1.6000000238,
    "max_price": 1.7300000191,
    "days_with_data": 5
  },
  {
    "week": "2024-07-29T00:00:00.000",
    "avg_price": 1.8139999628,
    "min_price": 1.6699999571,
    "max_price": 1.9199999571,
    "days_with_data": 5
  },
  {
    "week": "2024-08-05T00:00:00.000",
    "avg_price": 1.8130000114,
    "min_price": 1.6649999619,
    "max_price": 1.8799999952,
    "days_with_data": 5
  },
  {
    "week": "2024-08-12T00:00:00.000",
    "avg_price": 2.374000001,
    "min_price": 1.8700000048,
    "max_price": 2.8299999237,
    "days_with_data": 5
  },
  {
    "week": "2024-08-19T00:00:00.000",
    "avg_price": 3.2959999561,
    "min_price": 3.0999999046,
    "max_price": 3.5,
    "days_with_data": 5
  },
  {
    "week": "2024-08-26T00:00:00.000",
    "avg_price": 3.0159999847,
    "min_price": 2.6300001144,
    "max_price": 3.3299999237,
    "days_with_data": 5
  },
  {
    "week": "2024-09-02T00:00:00.000",
    "avg_price": 2.6337500215,
    "min_price": 2.5,
    "max_price": 2.8650000095,
    "days_with_data": 4
  },
  {
    "week": "2024-09-09T00:00:00.000",
    "avg_price": 2.6920000076,
    "min_price": 2.5099999905,
    "max_price": 2.9900000095,
    "days_with_data": 5
  },
  {
    "week": "2024-09-16T00:00:00.000",
    "avg_price": 3.0179999828,
    "min_price": 2.9100000858,
    "max_price": 3.0899999142,
    "days_with_data": 5
  },
  {
    "week": "2024-09-23T00:00:00.000",
    "avg_price": 2.8880000114,
    "min_price": 2.8199999332,
    "max_price": 2.9600000381,
    "days_with_data": 5
  },
  {
    "week": "2024-09-30T00:00:00.000",
    "avg_price": 3.4459999561,
    "min_price": 2.7799999714,
    "max_price": 4.0399999619,
    "days_with_data": 5
  },
  {
    "week": "2024-10-07T00:00:00.000",
    "avg_price": 3.8760000706,
    "min_price": 3.6900000572,
    "max_price": 4.0700001717,
    "days_with_data": 5
  },
  {
    "week": "2024-10-14T00:00:00.000",
    "avg_price": 4.1380000114,
    "min_price": 4.0,
    "max_price": 4.2600002289,
    "days_with_data": 5
  },
  {
    "week": "2024-10-21T00:00:00.000",
    "avg_price": 3.8980000019,
    "min_price": 3.7799999714,
    "max_price": 4.0599999428,
    "days_with_data": 5
  },
  {
    "week": "2024-10-28T00:00:00.000",
    "avg_price": 4.0880000114,
    "min_price": 4.0199999809,
    "max_price": 4.1999998093,
    "days_with_data": 5
  },
  {
    "week": "2024-11-04T00:00:00.000",
    "avg_price": 4.0160000324,
    "min_price": 3.4100000858,
    "max_price": 4.3499999046,
    "days_with_data": 5
  },
  {
    "week": "2024-11-11T00:00:00.000",
    "avg_price": 3.171999979,
    "min_price": 3.0399999619,
    "max_price": 3.3299999237,
    "days_with_data": 5
  },
  {
    "week": "2024-11-18T00:00:00.000",
    "avg_price": 3.313999939,
    "min_price": 3.2100000381,
    "max_price": 3.3699998856,
    "days_with_data": 5
  },
  {
    "week": "2024-11-25T00:00:00.000",
    "avg_price": 3.4475000501,
    "min_price": 3.4000000954,
    "max_price": 3.4900000095,
    "days_with_data": 4
  },
  {
    "week": "2024-12-02T00:00:00.000",
    "avg_price": 3.4080000401,
    "min_price": 3.3599998951,
    "max_price": 3.4300000668,
    "days_with_data": 5
  },
  {
    "week": "2024-12-09T00:00:00.000",
    "avg_price": 3.1399999619,
    "min_price": 3.0,
    "max_price": 3.2999999523,
    "days_with_data": 5
  },
  {
    "week": "2024-12-16T00:00:00.000",
    "avg_price": 3.1800000191,
    "min_price": 3.1199998856,
    "max_price": 3.2300000191,
    "days_with_data": 5
  },
  {
    "week": "2024-12-23T00:00:00.000",
    "avg_price": 3.2574999928,
    "min_price": 3.1900000572,
    "max_price": 3.3099999428,
    "days_with_data": 4
  },
  {
    "week": "2024-12-30T00:00:00.000",
    "avg_price": 3.1900000572,
    "min_price": 3.1300001144,
    "max_price": 3.2899999619,
    "days_with_data": 4
  },
  {
    "week": "2025-01-06T00:00:00.000",
    "avg_price": 3.5650000572,
    "min_price": 3.3800001144,
    "max_price": 3.6400001049,
    "days_with_data": 4
  },
  {
    "week": "2025-01-13T00:00:00.000",
    "avg_price": 3.9180000305,
    "min_price": 3.7200000286,
    "max_price": 4.0799999237,
    "days_with_data": 5
  },
  {
    "week": "2025-01-20T00:00:00.000",
    "avg_price": 4.5124999285,
    "min_price": 4.2399997711,
    "max_price": 4.8200001717,
    "days_with_data": 4
  },
  {
    "week": "2025-01-27T00:00:00.000",
    "avg_price": 4.493999958,
    "min_price": 4.3899998665,
    "max_price": 4.6100001335,
    "days_with_data": 5
  },
  {
    "week": "2025-02-03T00:00:00.000",
    "avg_price": 4.4399999619,
    "min_price": 4.3099999428,
    "max_price": 4.6599998474,
    "days_with_data": 5
  },
  {
    "week": "2025-02-10T00:00:00.000",
    "avg_price": 4.4579999924,
    "min_price": 4.3800001144,
    "max_price": 4.5399999619,
    "days_with_data": 5
  },
  {
    "week": "2025-02-17T00:00:00.000",
    "avg_price": 4.4624999762,
    "min_price": 4.4000000954,
    "max_price": 4.5500001907,
    "days_with_data": 4
  },
  {
    "week": "2025-02-24T00:00:00.000",
    "avg_price": 4.1879999638,
    "min_price": 3.9700000286,
    "max_price": 4.3299999237,
    "days_with_data": 5
  },
  {
    "week": "2025-03-03T00:00:00.000",
    "avg_price": 3.7000000477,
    "min_price": 3.6400001049,
    "max_price": 3.8299999237,
    "days_with_data": 5
  },
  {
    "week": "2025-03-10T00:00:00.000",
    "avg_price": 3.4960000038,
    "min_price": 3.3599998951,
    "max_price": 3.6600000858,
    "days_with_data": 5
  },
  {
    "week": "2025-03-17T00:00:00.000",
    "avg_price": 3.7200000286,
    "min_price": 3.6600000858,
    "max_price": 3.8099999428,
    "days_with_data": 5
  },
  {
    "week": "2025-03-24T00:00:00.000",
    "avg_price": 3.7399999619,
    "min_price": 3.5899999142,
    "max_price": 3.8699998856,
    "days_with_data": 5
  },
  {
    "week": "2025-03-31T00:00:00.000",
    "avg_price": 3.5219999313,
    "min_price": 3.3299999237,
    "max_price": 3.5899999142,
    "days_with_data": 5
  },
  {
    "week": "2025-04-07T00:00:00.000",
    "avg_price": 3.5320000648,
    "min_price": 3.2100000381,
    "max_price": 3.6800000668,
    "days_with_data": 5
  },
  {
    "week": "2025-04-14T00:00:00.000",
    "avg_price": 3.6675000191,
    "min_price": 3.5999999046,
    "max_price": 3.7200000286,
    "days_with_data": 4
  },
  {
    "week": "2025-04-21T00:00:00.000",
    "avg_price": 3.4120000362,
    "min_price": 3.3199999332,
    "max_price": 3.4700000286,
    "days_with_data": 5
  },
  {
    "week": "2025-04-28T00:00:00.000",
    "avg_price": 3.3960000038,
    "min_price": 3.3199999332,
    "max_price": 3.4700000286,
    "days_with_data": 5
  },
  {
    "week": "2025-05-05T00:00:00.000",
    "avg_price": 3.5459999561,
    "min_price": 3.3499999046,
    "max_price": 3.7699999809,
    "days_with_data": 5
  },
  {
    "week": "2025-05-12T00:00:00.000",
    "avg_price": 3.428000021,
    "min_price": 3.3099999428,
    "max_price": 3.5499999523,
    "days_with_data": 5
  },
  {
    "week": "2025-05-19T00:00:00.000",
    "avg_price": 3.4559999943,
    "min_price": 3.1900000572,
    "max_price": 3.6900000572,
    "days_with_data": 5
  },
  {
    "week": "2025-05-26T00:00:00.000",
    "avg_price": 3.1566667557,
    "min_price": 3.1300001144,
    "max_price": 3.2100000381,
    "days_with_data": 3
  }
]