{
  "balance_sheet": {
    "2025-03-31 00:00:00": {
      "Treasury Shares Number": "75178732.0",
      "Ordinary Shares Number": "4216254914.0",
      "Share Issued": "4291433646.0",
      "Net Debt": "141392000000.0",
      "Total Debt": "167714000000.0",
      "Tangible Book Value": "-89693000000.0",
      "Invested Capital": "244371000000.0",
      "Working Capital": "-23713000000.0",
      "Net Tangible Assets": "-89693000000.0",
      "Capital Lease Obligations": "24065000000.0",
      "Common Stock Equity": "100722000000.0",
      "Total Capitalization": "221742000000.0",
      "Total Equity Gross Minority Interest": "102037000000.0",
      "Minority Interest": "1315000000.0",
      "Stockholders Equity": "100722000000.0",
      "Other Equity Interest": "534000000.0",
      "Gains Losses Not Affecting Retained Earnings": "-1489000000.0",
      "Other Equity Adjustments": "-1489000000.0",
      "Treasury Stock": "3295000000.0",
      "Retained Earnings": "91128000000.0",
      "Additional Paid In Capital": "13415000000.0",
      "Capital Stock": "429000000.0",
      "Common Stock": "429000000.0",
      "Preferred Stock": "0.0",
      "Total Liabilities Net Minority Interest": "278327000000.0",
      "Total Non Current Liabilities Net Minority Interest": "217261000000.0",
      "Other Non Current Liabilities": "18426000000.0",
      "Employee Benefits": "11793000000.0",
      "Non Current Deferred Liabilities": "46643000000.0",
      "Non Current Deferred Taxes Liabilities": "46643000000.0",
      "Long Term Debt And Capital Lease Obligation": "140399000000.0",
      "Long Term Capital Lease Obligation": "19379000000.0",
      "Long Term Debt": "121020000000.0",
      "Current Liabilities": "61066000000.0",
      "Other Current Liabilities": "14338000000.0",
      "Current Deferred Liabilities": "0",
      "Current Deferred Revenue": "0",
      "Current Debt And Capital Lease Obligation": "27315000000.0",
      "Current Capital Lease Obligation": "4686000000.0",
      "Current Debt": "22629000000.0",
      "Other Current Borrowings": "22629000000.0",
      "Commercial Paper": "0",
      "Payables And Accrued Expenses": "19413000000.0",
      "Current Accrued Expenses": "0",
      "Interest Payable": "0",
      "Payables": "0",
      "Dividends Payable": "0",
      "Total Tax Payable": "0",
      "Accounts Payable": "0",
      "Total Assets": "380364000000.0",
      "Total Non Current Assets": "343011000000.0",
      "Other Non Current Assets": "19678000000.0",
      "Investments And Advances": "820000000.0",
      "Long Term Equity Investment": "820000000.0",
      "Goodwill And Other Intangible Assets": "190415000000.0",
      "Other Intangible Assets": "167573000000.0",
      "Goodwill": "22842000000.0",
      "Net PPE": "132098000000.0",
      "Accumulated Depreciation": "-223965000000.0",
      "Gross PPE": "356063000000.0",
      "Leases": "0",
      "Construction In Progress": "0",
      "Other Properties": "356063000000.0",
      "Machinery Furniture Equipment": "0",
      "Buildings And Improvements": "0",
      "Land And Improvements": "0",
      "Properties": "0",
      "Current Assets": "37353000000.0",
      "Other Current Assets": "7010000000.0",
      "Hedging Assets Current": "0",
      "Current Deferred Assets": "0",
      "Restricted Cash": "0",
      "Prepaid Assets": "0",
      "Inventory": "2197000000.0",
      "Receivables": "25889000000.0",
      "Accounts Receivable": "25889000000.0",
      "Allowance For Doubtful Accounts Receivable": "-1144000000.0",
      "Gross Accounts Receivable": "27033000000.0",
      "Cash Cash Equivalents And Short Term Investments": "2257000000.0",
      "Cash And Cash Equivalents": "2257000000.0"
    },
    "2024-12-31 00:00:00": {
      "Treasury Shares Number": "81753488.0",
      "Ordinary Shares Number": "4209680158.0",
      "Share Issued": "4291433646.0",
      "Net Debt": "139820000000.0",
      "Total Debt": "168357000000.0",
      "Tangible Book Value": "-91346000000.0",
      "Invested Capital": "243251000000.0",
      "Working Capital": "-24248000000.0",
      "Net Tangible Assets": "-91346000000.0",
      "Capital Lease Obligations": "24343000000.0",
      "Common Stock Equity": "99237000000.0",
      "Total Capitalization": "220618000000.0",
      "Total Equity Gross Minority Interest": "100575000000.0",
      "Minority Interest": "1338000000.0",
      "Stockholders Equity": "99237000000.0",
      "Other Equity Interest": "738000000.0",
      "Gains Losses Not Affecting Retained Earnings": "-923000000.0",
      "Other Equity Adjustments": "-923000000.0",
      "Treasury Stock": "3583000000.0",
      "Retained Earnings": "89110000000.0",
      "Additional Paid In Capital": "13466000000.0",
      "Capital Stock": "429000000.0",
      "Common Stock": "429000000.0",
      "Preferred Stock": "0.0",
      "Total Liabilities Net Minority Interest": "284136000000.0",
      "Total Non Current Liabilities Net Minority Interest": "219365000000.0",
      "Other Non Current Liabilities": "19327000000.0",
      "Employee Benefits": "11997000000.0",
      "Non Current Deferred Liabilities": "46732000000.0",
      "Non Current Deferred Taxes Liabilities": "46732000000.0",
      "Long Term Debt And Capital Lease Obligation": "141309000000.0",
      "Long Term Capital Lease Obligation": "19928000000.0",
      "Long Term Debt": "121381000000.0",
      "Current Liabilities": "64771000000.0",
      "Other Current Liabilities": "3979000000.0",
      "Current Deferred Liabilities": "7492000000.0",
      "Current Deferred Revenue": "7492000000.0",
      "Current Debt And Capital Lease Obligation": "27048000000.0",
      "Current Capital Lease Obligation": "4415000000.0",
      "Current Debt": "22633000000.0",
      "Other Current Borrowings": "22633000000.0",
      "Commercial Paper": "0",
      "Payables And Accrued Expenses": "26252000000.0",
      "Current Accrued Expenses": "11047000000.0",
      "Interest Payable": "1553000000.0",
      "Payables": "15205000000.0",
      "Dividends Payable": "2878000000.0",
      "Total Tax Payable": "1902000000.0",
      "Accounts Payable": "10425000000.0",
      "Total Assets": "384711000000.0",
      "Total Non Current Assets": "344188000000.0",
      "Other Non Current Assets": "19769000000.0",
      "Investments And Advances": "842000000.0",
      "Long Term Equity Investment": "842000000.0",
      "Goodwill And Other Intangible Assets": "190583000000.0",
      "Other Intangible Assets": "167742000000.0",
      "Goodwill": "22841000000.0",
      "Net PPE": "132994000000.0",
      "Accumulated Depreciation": "-222884000000.0",
      "Gross PPE": "355878000000.0",
      "Leases": "10562000000.0",
      "Construction In Progress": "9424000000.0",
      "Other Properties": "107282000000.0",
      "Machinery Furniture Equipment": "188740000000.0",
      "Buildings And Improvements": "39130000000.0",
      "Land And Improvements": "740000000.0",
      "Properties": "0.0",
      "Current Assets": "40523000000.0",
      "Other Current Assets": "1793000000.0",
      "Hedging Assets Current": "2118000000.0",
      "Current Deferred Assets": "2932000000.0",
      "Restricted Cash": "319000000.0",
      "Prepaid Assets": "811000000.0",
      "Inventory": "2247000000.0",
      "Receivables": "26109000000.0",
      "Accounts Receivable": "26109000000.0",
      "Allowance For Doubtful Accounts Receivable": "-1152000000.0",
      "Gross Accounts Receivable": "27261000000.0",
      "Cash Cash Equivalents And Short Term Investments": "4194000000.0",
      "Cash And Cash Equivalents": "4194000000.0"
    },
    "2024-09-30 00:00:00": {
      "Treasury Shares Number": "81807376.0",
      "Ordinary Shares Number": "4209626270.0",
      "Share Issued": "4291433646.0",
      "Net Debt": "145654000000.0",
      "Total Debt": "174200000000.0",
      "Tangible Book Value": "-93673000000.0",
      "Invested Capital": "246967000000.0",
      "Working Capital": "-21175000000.0",
      "Net Tangible Assets": "-93673000000.0",
      "Capital Lease Obligations": "23559000000.0",
      "Common Stock Equity": "96326000000.0",
      "Total Capitalization": "225204000000.0",
      "Total Equity Gross Minority Interest": "97668000000.0",
      "Minority Interest": "1342000000.0",
      "Stockholders Equity": "96326000000.0",
      "Other Equity Interest": "710000000.0",
      "Gains Losses Not Affecting Retained Earnings": "-1665000000.0",
      "Other Equity Adjustments": "-1665000000.0",
      "Treasury Stock": "3585000000.0",
      "Retained Earnings": "86958000000.0",
      "Additional Paid In Capital": "13479000000.0",
      "Capital Stock": "429000000.0",
      "Common Stock": "429000000.0",
      "Preferred Stock": "0.0",
      "Total Liabilities Net Minority Interest": "283496000000.0",
      "Total Non Current Liabilities Net Minority Interest": "221680000000.0",
      "Other Non Current Liabilities": "14946000000.0",
      "Employee Benefits": "12744000000.0",
      "Non Current Deferred Liabilities": "45865000000.0",
      "Non Current Deferred Taxes Liabilities": "45865000000.0",
      "Long Term Debt And Capital Lease Obligation": "148125000000.0",
      "Long Term Capital Lease Obligation": "19247000000.0",
      "Long Term Debt": "128878000000.0",
      "Current Liabilities": "61816000000.0",
      "Other Current Liabilities": "13519000000.0",
      "Current Deferred Liabilities": "0",
      "Current Deferred Revenue": "0",
      "Current Debt And Capital Lease Obligation": "26075000000.0",
      "Current Capital Lease Obligation": "4312000000.0",
      "Current Debt": "21763000000.0",
      "Other Current Borrowings": "21763000000.0",
      "Commercial Paper": "0",
      "Payables And Accrued Expenses": "22222000000.0",
      "Current Accrued Expenses": "0",
      "Interest Payable": "0",
      "Payables": "0",
      "Dividends Payable": "0",
      "Total Tax Payable": "0",
      "Accounts Payable": "0",
      "Total Assets": "381164000000.0",
      "Total Non Current Assets": "340523000000.0",
      "Other Non Current Assets": "18516000000.0",
      "Investments And Advances": "867000000.0",
      "Long Term Equity Investment": "867000000.0",
      "Goodwill And Other Intangible Assets": "189999000000.0",
      "Other Intangible Assets": "167155000000.0",
      "Goodwill": "22844000000.0",
      "Net PPE": "131141000000.0",
      "Accumulated Depreciation": "-220027000000.0",
      "Gross PPE": "351168000000.0",
      "Leases": "0",
      "Construction In Progress": "0",
      "Other Properties": "351168000000.0",
      "Machinery Furniture Equipment": "0",
      "Buildings And Improvements": "0",
      "Land And Improvements": "0",
      "Properties": "0",
      "Current Assets": "40641000000.0",
      "Other Current Assets": "7177000000.0",
      "Hedging Assets Current": "0",
      "Current Deferred Assets": "0",
      "Restricted Cash": "0",
      "Prepaid Assets": "0",
      "Inventory": "2523000000.0",
      "Receivables": "25954000000.0",
      "Accounts Receivable": "25954000000.0",
      "Allowance For Doubtful Accounts Receivable": "-1086000000.0",
      "Gross Accounts Receivable": "27040000000.0",
      "Cash Cash Equivalents And Short Term Investments": "4987000000.0",
      "Cash And Cash Equivalents": "4987000000.0"
    },
    "2024-06-30 00:00:00": {
      "Treasury Shares Number": "81913650.0",
      "Ordinary Shares Number": "4209519996.0",
      "Share Issued": "4291433646.0",
      "Net Debt": "146845000000.0",
      "Total Debt": "172980000000.0",
      "Tangible Book Value": "-93641000000.0",
      "Invested Capital": "245449000000.0",
      "Working Capital": "-22750000000.0",
      "Net Tangible Assets": "-93641000000.0",
      "Capital Lease Obligations": "23703000000.0",
      "Common Stock Equity": "96172000000.0",
      "Total Capitalization": "222194000000.0",
      "Total Equity Gross Minority Interest": "97539000000.0",
      "Minority Interest": "1367000000.0",
      "Stockholders Equity": "96172000000.0",
      "Other Equity Interest": "577000000.0",
      "Gains Losses Not Affecting Retained Earnings": "-1287000000.0",
      "Other Equity Adjustments": "-1287000000.0",
      "Treasury Stock": "3590000000.0",
      "Retained Earnings": "86504000000.0",
      "Additional Paid In Capital": "13539000000.0",
      "Capital Stock": "429000000.0",
      "Common Stock": "429000000.0",
      "Preferred Stock": "0.0",
      "Total Liabilities Net Minority Interest": "281607000000.0",
      "Total Non Current Liabilities Net Minority Interest": "220801000000.0",
      "Other Non Current Liabilities": "16429000000.0",
      "Employee Benefits": "12812000000.0",
      "Non Current Deferred Liabilities": "46082000000.0",
      "Non Current Deferred Taxes Liabilities": "46082000000.0",
      "Long Term Debt And Capital Lease Obligation": "145478000000.0",
      "Long Term Capital Lease Obligation": "19456000000.0",
      "Long Term Debt": "126022000000.0",
      "Current Liabilities": "60806000000.0",
      "Other Current Liabilities": "13577000000.0",
      "Current Deferred Liabilities": "0",
      "Current Deferred Revenue": "0",
      "Current Debt And Capital Lease Obligation": "27502000000.0",
      "Current Capital Lease Obligation": "4247000000.0",
      "Current Debt": "23255000000.0",
      "Other Current Borrowings": "23255000000.0",
      "Commercial Paper": "0",
      "Payables And Accrued Expenses": "19727000000.0",
      "Current Accrued Expenses": "0",
      "Interest Payable": "0",
      "Payables": "0",
      "Dividends Payable": "0",
      "Total Tax Payable": "0",
      "Accounts Payable": "0",
      "Total Assets": "379146000000.0",
      "Total Non Current Assets": "341090000000.0",
      "Other Non Current Assets": "18415000000.0",
      "Investments And Advances": "908000000.0",
      "Long Term Equity Investment": "908000000.0",
      "Goodwill And Other Intangible Assets": "189813000000.0",
      "Other Intangible Assets": "166971000000.0",
      "Goodwill": "22842000000.0",
      "Net PPE": "131954000000.0",
      "Accumulated Depreciation": "-217088000000.0",
      "Gross PPE": "349042000000.0",
      "Leases": "0",
      "Construction In Progress": "0",
      "Other Properties": "349042000000.0",
      "Machinery Furniture Equipment": "0",
      "Buildings And Improvements": "0",
      "Land And Improvements": "0",
      "Properties": "0",
      "Current Assets": "38056000000.0",
      "Other Current Assets": "8176000000.0",
      "Hedging Assets Current": "0",
      "Current Deferred Assets": "0",
      "Restricted Cash": "0",
      "Prepaid Assets": "0",
      "Inventory": "1841000000.0",
      "Receivables": "25607000000.0",
      "Accounts Receivable": "25607000000.0",
      "Allowance For Doubtful Accounts Receivable": "-1095000000.0",
      "Gross Accounts Receivable": "26702000000.0",
      "Cash Cash Equivalents And Short Term Investments": "2432000000.0",
      "Cash And Cash Equivalents": "2432000000.0"
    },
    "2024-03-31 00:00:00": {
      "Treasury Shares Number": "82178752.0",
      "Ordinary Shares Number": "4209254894.0",
      "Share Issued": "4291433646.0",
      "Net Debt": "149333000000.0",
      "Total Debt": "175634000000.0",
      "Tangible Book Value": "-95454000000.0",
      "Invested Capital": "246032000000.0",
      "Working Capital": "-15674000000.0",
      "Net Tangible Assets": "-95454000000.0",
      "Capital Lease Obligations": "23936000000.0",
      "Common Stock Equity": "94334000000.0",
      "Total Capitalization": "230438000000.0",
      "Total Equity Gross Minority Interest": "95726000000.0",
      "Minority Interest": "1392000000.0",
      "Stockholders Equity": "94334000000.0",
      "Other Equity Interest": "421000000.0",
      "Gains Losses Not Affecting Retained Earnings": "-1199000000.0",
      "Other Equity Adjustments": "-1199000000.0",
      "Treasury Stock": "3602000000.0",
      "Retained Earnings": "84714000000.0",
      "Additional Paid In Capital": "13571000000.0",
      "Capital Stock": "429000000.0",
      "Common Stock": "429000000.0",
      "Preferred Stock": "0.0",
      "Total Liabilities Net Minority Interest": "284432000000.0",
      "Total Non Current Liabilities Net Minority Interest": "230801000000.0",
      "Other Non Current Liabilities": "16258000000.0",
      "Employee Benefits": "12805000000.0",
      "Non Current Deferred Liabilities": "45980000000.0",
      "Non Current Deferred Taxes Liabilities": "45980000000.0",
      "Long Term Debt And Capital Lease Obligation": "155758000000.0",
      "Long Term Capital Lease Obligation": "19654000000.0",
      "Long Term Debt": "136104000000.0",
      "Current Liabilities": "53631000000.0",
      "Other Current Liabilities": "13616000000.0",
      "Current Deferred Liabilities": "0",
      "Current Deferred Revenue": "0",
      "Current Debt And Capital Lease Obligation": "19876000000.0",
      "Current Capital Lease Obligation": "4282000000.0",
      "Current Debt": "15594000000.0",
      "Other Current Borrowings": "15594000000.0",
      "Commercial Paper": "0",
      "Payables And Accrued Expenses": "20139000000.0",
      "Current Accrued Expenses": "0",
      "Interest Payable": "0",
      "Payables": "0",
      "Dividends Payable": "0",
      "Total Tax Payable": "0",
      "Accounts Payable": "0",
      "Total Assets": "380158000000.0",
      "Total Non Current Assets": "342201000000.0",
      "Other Non Current Assets": "19258000000.0",
      "Investments And Advances": "941000000.0",
      "Long Term Equity Investment": "941000000.0",
      "Goodwill And Other Intangible Assets": "189788000000.0",
      "Other Intangible Assets": "166946000000.0",
      "Goodwill": "22842000000.0",
      "Net PPE": "132214000000.0",
      "Accumulated Depreciation": "-214403000000.0",
      "Gross PPE": "346617000000.0",
      "Leases": "0",
      "Construction In Progress": "0",
      "Other Properties": "346617000000.0",
      "Machinery Furniture Equipment": "0",
      "Buildings And Improvements": "0",
      "Land And Improvements": "0",
      "Properties": "0",
      "Current Assets": "37957000000.0",
      "Other Current Assets": "8197000000.0",
      "Hedging Assets Current": "0",
      "Current Deferred Assets": "0",
      "Restricted Cash": "0",
      "Prepaid Assets": "0",
      "Inventory": "2076000000.0",
      "Receivables": "25319000000.0",
      "Accounts Receivable": "25319000000.0",
      "Allowance For Doubtful Accounts Receivable": "-1061000000.0",
      "Gross Accounts Receivable": "26380000000.0",
      "Cash Cash Equivalents And Short Term Investments": "2365000000.0",
      "Cash And Cash Equivalents": "2365000000.0"
    },
    "2023-12-31 00:00:00": {
      "Treasury Shares Number": "0",
      "Ordinary Shares Number": "0",
      "Share Issued": "0",
      "Net Debt": "0",
      "Total Debt": "0",
      "Tangible Book Value": "0",
      "Invested Capital": "0",
      "Working Capital": "0",
      "Net Tangible Assets": "0",
      "Capital Lease Obligations": "0",
      "Common Stock Equity": "0",
      "Total Capitalization": "0",
      "Total Equity Gross Minority Interest": "0",
      "Minority Interest": "0",
      "Stockholders Equity": "0",
      "Other Equity Interest": "0",
      "Gains Losses Not Affecting Retained Earnings": "0",
      "Other Equity Adjustments": "0",
      "Treasury Stock": "0",
      "Retained Earnings": "0",
      "Additional Paid In Capital": "0",
      "Capital Stock": "0",
      "Common Stock": "0",
      "Preferred Stock": "0",
      "Total Liabilities Net Minority Interest": "0",
      "Total Non Current Liabilities Net Minority Interest": "0",
      "Other Non Current Liabilities": "0",
      "Employee Benefits": "0",
      "Non Current Deferred Liabilities": "0",
      "Non Current Deferred Taxes Liabilities": "0",
      "Long Term Debt And Capital Lease Obligation": "0",
      "Long Term Capital Lease Obligation": "0",
      "Long Term Debt": "0",
      "Current Liabilities": "0",
      "Other Current Liabilities": "0",
      "Current Deferred Liabilities": "6955000000.0",
      "Current Deferred Revenue": "6955000000.0",
      "Current Debt And Capital Lease Obligation": "0",
      "Current Capital Lease Obligation": "0",
      "Current Debt": "0",
      "Other Current Borrowings": "0",
      "Commercial Paper": "0.0",
      "Payables And Accrued Expenses": "0",
      "Current Accrued Expenses": "10820000000.0",
      "Interest Payable": "1570000000.0",
      "Payables": "15454000000.0",
      "Dividends Payable": "2821000000.0",
      "Total Tax Payable": "2612000000.0",
      "Accounts Payable": "10021000000.0",
      "Total Assets": "0",
      "Total Non Current Assets": "0",
      "Other Non Current Assets": "0",
      "Investments And Advances": "0",
      "Long Term Equity Investment": "0",
      "Goodwill And Other Intangible Assets": "0",
      "Other Intangible Assets": "0",
      "Goodwill": "0",
      "Net PPE": "0",
      "Accumulated Depreciation": "0",
      "Gross PPE": "0",
      "Leases": "10355000000.0",
      "Construction In Progress": "12092000000.0",
      "Other Properties": "0",
      "Machinery Furniture Equipment": "181615000000.0",
      "Buildings And Improvements": "36940000000.0",
      "Land And Improvements": "751000000.0",
      "Properties": "0.0",
      "Current Assets": "0",
      "Other Current Assets": "0",
      "Hedging Assets Current": "1406000000.0",
      "Current Deferred Assets": "2756000000.0",
      "Restricted Cash": "1244000000.0",
      "Prepaid Assets": "550000000.0",
      "Inventory": "0",
      "Receivables": "0",
      "Accounts Receivable": "0",
      "Allowance For Doubtful Accounts Receivable": "0",
      "Gross Accounts Receivable": "0",
      "Cash Cash Equivalents And Short Term Investments": "0",
      "Cash And Cash Equivalents": "0"
    }
  },
  "income_statement": {
    "2025-03-31 00:00:00": {
      "Tax Effect Of Unusual Items": "20700000.0",
      "Tax Rate For Calcs": "0.23",
      "Normalized EBITDA": "12592000000.0",
      "Total Unusual Items": "90000000.0",
      "Total Unusual Items Excluding Goodwill": "90000000.0",
      "Net Income From Continuing Operation Net Minority Interest": "4879000000.0",
      "Reconciled Depreciation": "4577000000.0",
      "Reconciled Cost Of Revenue": "13056000000.0",
      "EBITDA": "12682000000.0",
      "EBIT": "8105000000.0",
      "Net Interest Income": "-1569000000.0",
      "Interest Expense": "1632000000.0",
      "Interest Income": "63000000.0",
      "Normalized Income": "4809700000.0",
      "Net Income From Continuing And Discontinued Operation": "4879000000.0",
      "Total Expenses": "25507000000.0",
      "Total Operating Income As Reported": "7978000000.0",
      "Diluted Average Shares": "4226000000.0",
      "Basic Average Shares": "4222000000.0",
      "Diluted EPS": "1.15",
      "Basic EPS": "1.16",
      "Diluted NI Availto Com Stockholders": "4879000000.0",
      "Net Income Common Stockholders": "4879000000.0",
      "Net Income": "4879000000.0",
      "Minority Interests": "-104000000.0",
      "Net Income Including Noncontrolling Interests": "4983000000.0",
      "Net Income Continuous Operations": "4983000000.0",
      "Tax Provision": "1490000000.0",
      "Pretax Income": "6473000000.0",
      "Other Income Expense": "64000000.0",
      "Other Non Operating Income Expenses": "-32000000.0",
      "Special Income Charges": "90000000.0",
      "Other Special Charges": "-90000000.0",
      "Earnings From Equity Interest": "6000000.0",
      "Net Non Operating Interest Income Expense": "-1569000000.0",
      "Interest Expense Non Operating": "1632000000.0",
      "Interest Income Non Operating": "63000000.0",
      "Operating Income": "7978000000.0",
      "Operating Expense": "12451000000.0",
      "Depreciation Amortization Depletion Income Statement": "4577000000.0",
      "Depreciation And Amortization In Income Statement": "4577000000.0",
      "Selling General And Administration": "7874000000.0",
      "Gross Profit": "20429000000.0",
      "Cost Of Revenue": "13056000000.0",
      "Total Revenue": "33485000000.0",
      "Operating Revenue": "33485000000.0"
    },
    "2024-12-31 00:00:00": {
      "Tax Effect Of Unusual Items": "21252131.546894",
      "Tax Rate For Calcs": "0.221376",
      "Normalized EBITDA": "12622000000.0",
      "Total Unusual Items": "96000000.0",
      "Total Unusual Items Excluding Goodwill": "96000000.0",
      "Net Income From Continuing Operation Net Minority Interest": "5005000000.0",
      "Reconciled Depreciation": "4506000000.0",
      "Reconciled Cost Of Revenue": "15514000000.0",
      "EBITDA": "12718000000.0",
      "EBIT": "8212000000.0",
      "Net Interest Income": "-1566000000.0",
      "Interest Expense": "1644000000.0",
      "Interest Income": "78000000.0",
      "Normalized Income": "4930252131.546894",
      "Net Income From Continuing And Discontinued Operation": "5005000000.0",
      "Total Expenses": "28260000000.0",
      "Total Operating Income As Reported": "7421000000.0",
      "Diluted Average Shares": "4227000000.0",
      "Basic Average Shares": "4222000000.0",
      "Diluted EPS": "1.18",
      "Basic EPS": "1.19",
      "Diluted NI Availto Com Stockholders": "5005000000.0",
      "Net Income Common Stockholders": "5005000000.0",
      "Net Income": "5005000000.0",
      "Minority Interests": "-109000000.0",
      "Net Income Including Noncontrolling Interests": "5114000000.0",
      "Net Income Continuous Operations": "5114000000.0",
      "Tax Provision": "1454000000.0",
      "Pretax Income": "6568000000.0",
      "Other Income Expense": "713000000.0",
      "Other Non Operating Income Expenses": "623000000.0",
      "Special Income Charges": "96000000.0",
      "Other Special Charges": "-96000000.0",
      "Earnings From Equity Interest": "-6000000.0",
      "Net Non Operating Interest Income Expense": "-1566000000.0",
      "Interest Expense Non Operating": "1644000000.0",
      "Interest Income Non Operating": "78000000.0",
      "Operating Income": "7421000000.0",
      "Operating Expense": "12746000000.0",
      "Depreciation Amortization Depletion Income Statement": "4506000000.0",
      "Depreciation And Amortization In Income Statement": "4506000000.0",
      "Selling General And Administration": "8240000000.0",
      "Gross Profit": "20167000000.0",
      "Cost Of Revenue": "15514000000.0",
      "Total Revenue": "35681000000.0",
      "Operating Revenue": "35681000000.0"
    },
    "2024-09-30 00:00:00": {
      "Tax Effect Of Unusual Items": "18630000.0",
      "Tax Rate For Calcs": "0.207",
      "Normalized EBITDA": "10342000000.0",
      "Total Unusual Items": "90000000.0",
      "Total Unusual Items Excluding Goodwill": "90000000.0",
      "Net Income From Continuing Operation Net Minority Interest": "3306000000.0",
      "Reconciled Depreciation": "4458000000.0",
      "Reconciled Cost Of Revenue": "13240000000.0",
      "EBITDA": "10432000000.0",
      "EBIT": "5974000000.0",
      "Net Interest Income": "-1575000000.0",
      "Interest Expense": "1672000000.0",
      "Interest Income": "97000000.0",
      "Normalized Income": "3234630000.0",
      "Net Income From Continuing And Discontinued Operation": "3306000000.0",
      "Total Expenses": "27404000000.0",
      "Total Operating Income As Reported": "5926000000.0",
      "Diluted Average Shares": "4225000000.0",
      "Basic Average Shares": "4220000000.0",
      "Diluted EPS": "0.78",
      "Basic EPS": "0.78",
      "Diluted NI Availto Com Stockholders": "3306000000.0",
      "Net Income Common Stockholders": "3306000000.0",
      "Net Income": "3306000000.0",
      "Minority Interests": "-105000000.0",
      "Net Income Including Noncontrolling Interests": "3411000000.0",
      "Net Income Continuous Operations": "3411000000.0",
      "Tax Provision": "891000000.0",
      "Pretax Income": "4302000000.0",
      "Other Income Expense": "-49000000.0",
      "Other Non Operating Income Expenses": "-115000000.0",
      "Special Income Charges": "90000000.0",
      "Other Special Charges": "-90000000.0",
      "Earnings From Equity Interest": "-24000000.0",
      "Net Non Operating Interest Income Expense": "-1575000000.0",
      "Interest Expense Non Operating": "1672000000.0",
      "Interest Income Non Operating": "97000000.0",
      "Operating Income": "5926000000.0",
      "Operating Expense": "14164000000.0",
      "Depreciation Amortization Depletion Income Statement": "4458000000.0",
      "Depreciation And Amortization In Income Statement": "4458000000.0",
      "Selling General And Administration": "9706000000.0",
      "Gross Profit": "20090000000.0",
      "Cost Of Revenue": "13240000000.0",
      "Total Revenue": "33330000000.0",
      "Operating Revenue": "33330000000.0"
    },
    "2024-06-30 00:00:00": {
      "Tax Effect Of Unusual Items": "19669000.0",
      "Tax Rate For Calcs": "0.221",
      "Normalized EBITDA": "12126000000.0",
      "Total Unusual Items": "89000000.0",
      "Total Unusual Items Excluding Goodwill": "89000000.0",
      "Net Income From Continuing Operation Net Minority Interest": "4593000000.0",
      "Reconciled Depreciation": "4483000000.0",
      "Reconciled Cost Of Revenue": "12471000000.0",
      "EBITDA": "12215000000.0",
      "EBIT": "7732000000.0",
      "Net Interest Income": "-1615000000.0",
      "Interest Expense": "1698000000.0",
      "Interest Income": "83000000.0",
      "Normalized Income": "4523669000.0",
      "Net Income From Continuing And Discontinued Operation": "4593000000.0",
      "Total Expenses": "24978000000.0",
      "Total Operating Income As Reported": "7818000000.0",
      "Diluted Average Shares": "4221000000.0",
      "Basic Average Shares": "4215000000.0",
      "Diluted EPS": "1.09",
      "Basic EPS": "1.09",
      "Diluted NI Availto Com Stockholders": "4593000000.0",
      "Net Income Common Stockholders": "4593000000.0",
      "Net Income": "4593000000.0",
      "Minority Interests": "-109000000.0",
      "Net Income Including Noncontrolling Interests": "4702000000.0",
      "Net Income Continuous Operations": "4702000000.0",
      "Tax Provision": "1332000000.0",
      "Pretax Income": "6034000000.0",
      "Other Income Expense": "-169000000.0",
      "Other Non Operating Income Expenses": "-244000000.0",
      "Special Income Charges": "89000000.0",
      "Other Special Charges": "-89000000.0",
      "Earnings From Equity Interest": "-14000000.0",
      "Net Non Operating Interest Income Expense": "-1615000000.0",
      "Interest Expense Non Operating": "1698000000.0",
      "Interest Income Non Operating": "83000000.0",
      "Operating Income": "7818000000.0",
      "Operating Expense": "12507000000.0",
      "Depreciation Amortization Depletion Income Statement": "4483000000.0",
      "Depreciation And Amortization In Income Statement": "4483000000.0",
      "Selling General And Administration": "8024000000.0",
      "Gross Profit": "20325000000.0",
      "Cost Of Revenue": "12471000000.0",
      "Total Revenue": "32796000000.0",
      "Operating Revenue": "32796000000.0"
    },
    "2024-03-31 00:00:00": {
      "Tax Effect Of Unusual Items": "24530000.0",
      "Tax Rate For Calcs": "0.223",
      "Normalized EBITDA": "12045000000.0",
      "Total Unusual Items": "110000000.0",
      "Total Unusual Items Excluding Goodwill": "110000000.0",
      "Net Income From Continuing Operation Net Minority Interest": "4602000000.0",
      "Reconciled Depreciation": "4445000000.0",
      "Reconciled Cost Of Revenue": "12872000000.0",
      "EBITDA": "12155000000.0",
      "EBIT": "7710000000.0",
      "Net Interest Income": "-1557000000.0",
      "Interest Expense": "1635000000.0",
      "Interest Income": "78000000.0",
      "Normalized Income": "4516530000.0",
      "Net Income From Continuing And Discontinued Operation": "4602000000.0",
      "Total Expenses": "25460000000.0",
      "Total Operating Income As Reported": "7521000000.0",
      "Diluted Average Shares": "4219000000.0",
      "Basic Average Shares": "4215000000.0",
      "Diluted EPS": "1.09",
      "Basic EPS": "1.09",
      "Diluted NI Availto Com Stockholders": "4602000000.0",
      "Net Income Common Stockholders": "4602000000.0",
      "Net Income": "4602000000.0",
      "Minority Interests": "-120000000.0",
      "Net Income Including Noncontrolling Interests": "4722000000.0",
      "Net Income Continuous Operations": "4722000000.0",
      "Tax Provision": "1353000000.0",
      "Pretax Income": "6075000000.0",
      "Other Income Expense": "111000000.0",
      "Other Non Operating Income Expenses": "10000000.0",
      "Special Income Charges": "110000000.0",
      "Other Special Charges": "-110000000.0",
      "Earnings From Equity Interest": "-9000000.0",
      "Net Non Operating Interest Income Expense": "-1557000000.0",
      "Interest Expense Non Operating": "1635000000.0",
      "Interest Income Non Operating": "78000000.0",
      "Operating Income": "7521000000.0",
      "Operating Expense": "12588000000.0",
      "Depreciation Amortization Depletion Income Statement": "4445000000.0",
      "Depreciation And Amortization In Income Statement": "4445000000.0",
      "Selling General And Administration": "8143000000.0",
      "Gross Profit": "20109000000.0",
      "Cost Of Revenue": "12872000000.0",
      "Total Revenue": "32981000000.0",
      "Operating Revenue": "32981000000.0"
    }
  }
}